IP2Proxy.py
ip2proxy-3.5.2.dist-info/licenses/AUTHORS
ip2proxy-3.5.2.dist-info/licenses/LICENSE.TXT
ip2proxy-3.5.2.dist-info/METADATA
ip2proxy-3.5.2.dist-info/WHEEL
ip2proxy-3.5.2.dist-info/top_level.txt
ip2proxy-3.5.2.dist-info/RECORD
